{
  "name": "textbooks/users/RUaGBPrXXoBSNI0hiZS8PHzCwLTN/67828e67043bba8378f55b740353980e0536b82126a6e4d1554d233de00369a8/pages/01.mmd/questions/0",
  "bucket": "my-book-study.appspot.com",
  "metageneration": 1,
  "generation": 1699195341891,
  "contentType": "text/markdown",
  "storageClass": "STANDARD",
  "downloadTokens": [],
  "etag": "fnn/617/CJbBJnf0vvyGffhAWjQ",
  "timeCreated": "2023-11-05T14:42:21.891Z",
  "updated": "2023-11-05T14:42:21.891Z",
  "size": 46,
  "md5Hash": "5m7zXFomrAWs3zXehgTMtg==",
  "crc32c": "3895156448"
}